aria3/__init__.py
aria3/cli.py
aria3/downloader.py
aria3/playlist_parser.py
aria3/prefetch_manager.py
aria3/streaming_cache.py
aria3/streaming_cli.py
aria3/streaming_config.py
aria3/streaming_server.py
aria3-0.1.1.dist-info/entry_points.txt
aria3-0.1.1.dist-info/METADATA
aria3-0.1.1.dist-info/WHEEL
aria3-0.1.1.dist-info/RECORD
