Metadata-Version: 2.3
Name: aria3
Version: 0.1.1
Summary: 高级多线程下载器与流媒体代理 - Advanced multi-threaded downloader and streaming proxy (aria2 replacement)
License: MIT
Keywords: download,multi-thread,streaming,proxy,hls,dash,aria2,replacement
Author: wmymz
Author-email: wmymz@icloud.com
Requires-Python: >=3.8,<4.0
Classifier: Development Status :: 4 - Beta
Classifier: Intended Audience :: Developers
Classifier: License :: OSI Approved :: MIT License
Classifier: Programming Language :: Python :: 3
Classifier: Programming Language :: Python :: 3.8
Classifier: Programming Language :: Python :: 3.9
Classifier: Programming Language :: Python :: 3.10
Classifier: Programming Language :: Python :: 3.11
Classifier: Programming Language :: Python :: 3.12
Classifier: Programming Language :: Python :: 3.13
Classifier: Topic :: Internet :: WWW/HTTP
Classifier: Topic :: Multimedia :: Video
Classifier: Topic :: Software Development :: Libraries :: Python Modules
Requires-Dist: aiofiles (>=0.7.0,<0.8.0)
Requires-Dist: fastapi (>=0.68.0,<0.69.0)
Requires-Dist: m3u8 (>=3.0.0,<4.0.0)
Requires-Dist: requests (>=2.25.0,<3.0.0)
Requires-Dist: tqdm (>=4.60.0,<5.0.0)
Requires-Dist: uvicorn (>=0.15.0,<0.16.0)
Project-URL: Homepage, https://github.com/qy527145/aria3
Project-URL: Repository, https://github.com/qy527145/aria3
